pyearthtools/zoo/__init__.py
pyearthtools/zoo/__main__.py
pyearthtools/zoo/config.py
pyearthtools/zoo/exceptions.py
pyearthtools/zoo/logger.py
pyearthtools/zoo/model.py
pyearthtools/zoo/models.yaml
pyearthtools/zoo/predict.py
pyearthtools/zoo/register.py
pyearthtools/zoo/utils.py
pyearthtools/zoo/warnings.py
pyearthtools/zoo/commands/__init__.py
pyearthtools/zoo/commands/commands.py
pyearthtools/zoo/commands/utils.py
pyearthtools_zoo-0.5.1.dist-info/METADATA
pyearthtools_zoo-0.5.1.dist-info/WHEEL
pyearthtools_zoo-0.5.1.dist-info/entry_points.txt
pyearthtools_zoo-0.5.1.dist-info/licenses/LICENSE
pyearthtools_zoo-0.5.1.dist-info/RECORD
