Metadata-Version: 2.4
Name: pyearthtools-zoo
Version: 0.5.1
Dynamic: Description
Dynamic: Description-Content-Type
Summary: PyEarthTools Models Registry
Project-URL: homepage, https://pyearthtools.readthedocs.io/
Project-URL: documentation, https://pyearthtools.readthedocs.io/
Project-URL: repository, https://github.com/ACCESS-Community-Hub/PyEarthTools
Maintainer-email: Tennessee Leeuwenburg <tennessee.leeuwenburg@bom.gov.au>
License-File: LICENSE
Keywords: pyearthtools
Classifier: License :: OSI Approved :: Apache Software License
Classifier: Operating System :: OS Independent
Classifier: Programming Language :: Python :: 3
Requires-Python: >=3.11
Requires-Dist: click
Requires-Dist: entrypoints
Requires-Dist: multiurl
Requires-Dist: pyearthtools-data>=0.5.0
Requires-Dist: pyearthtools-pipeline>=0.5.0
Requires-Dist: pyearthtools-training>=0.5.0
Requires-Dist: pyearthtools-utils>=0.5.0
Requires-Dist: tqdm
Provides-Extra: testing
Requires-Dist: black; extra == 'testing'
Requires-Dist: coverage; extra == 'testing'
Requires-Dist: pytest; extra == 'testing'
Requires-Dist: pytest-cov; extra == 'testing'
